safelogging/__init__.py
safelogging-0.1.0.dist-info/DESCRIPTION.rst
safelogging-0.1.0.dist-info/METADATA
safelogging-0.1.0.dist-info/RECORD
safelogging-0.1.0.dist-info/WHEEL
safelogging-0.1.0.dist-info/metadata.json
safelogging-0.1.0.dist-info/top_level.txt
