Metadata-Version: 2.0
Name: safelogging
Version: 0.1.0
Summary: Extensions to the standard python logging framework
Home-page: https://github.com/Procera/python-safelogging
Author: Pontus Andersson
Author-email: pontus.andersson@proceranetworks.com
License: MIT
Keywords: python safe logging syslog
Platform: UNKNOWN
Classifier: Development Status :: 3 - Alpha
Classifier: Intended Audience :: Developers
Classifier: Operating System :: POSIX :: Linux
Classifier: License :: OSI Approved :: MIT License
Classifier: Programming Language :: Python :: 2
Classifier: Programming Language :: Python :: 3
